andromeda/__init__.py
andromeda/andromeda_app.py
andromeda/config.py
andromeda/connect_db.py
andromeda/graphql.py
andromeda/logger.py
andromeda/logger_function.py
andromeda/storage.py
andromeda/tenant_details.py
andromeda/tenant_details_functions.py
tests/__init__.py
tests/test_graphql_functions.py
my_bot_library-0.0.3.dist-info/LICENSE.txt
my_bot_library-0.0.3.dist-info/METADATA
my_bot_library-0.0.3.dist-info/WHEEL
my_bot_library-0.0.3.dist-info/top_level.txt
my_bot_library-0.0.3.dist-info/RECORD
