Metadata-Version: 2.1
Name: my-bot-library
Version: 0.0.3
Summary: Andromeda Python library
Home-page: UNKNOWN
Author: Susheela
License: MIT
Keywords: andromeda
Platform: UNKNOWN
License-File: LICENSE.txt
